jupyterlab_cell_flash/__init__.py
jupyterlab_cell_flash/_version.py
jupyterlab_cell_flash-0.4.0.data/data/share/jupyter/labextensions/jupyterlab-cell-flash/package.json
jupyterlab_cell_flash-0.4.0.data/data/share/jupyter/labextensions/jupyterlab-cell-flash/schemas/jupyterlab-cell-flash/package.json.orig
jupyterlab_cell_flash-0.4.0.data/data/share/jupyter/labextensions/jupyterlab-cell-flash/schemas/jupyterlab-cell-flash/plugin.json
jupyterlab_cell_flash-0.4.0.data/data/share/jupyter/labextensions/jupyterlab-cell-flash/static/568.dd6e64dba97e1e4545f1.js
jupyterlab_cell_flash-0.4.0.data/data/share/jupyter/labextensions/jupyterlab-cell-flash/static/747.d6eefe979fcab7d67a7e.js
jupyterlab_cell_flash-0.4.0.data/data/share/jupyter/labextensions/jupyterlab-cell-flash/static/remoteEntry.ddd7c20c6f5f1624a054.js
jupyterlab_cell_flash-0.4.0.data/data/share/jupyter/labextensions/jupyterlab-cell-flash/static/style.js
jupyterlab_cell_flash-0.4.0.data/data/share/jupyter/labextensions/jupyterlab-cell-flash/static/third-party-licenses.json
jupyterlab_cell_flash-0.4.0.data/data/share/jupyter/labextensions/jupyterlab-cell-flash/install.json
jupyterlab_cell_flash-0.4.0.dist-info/METADATA
jupyterlab_cell_flash-0.4.0.dist-info/WHEEL
jupyterlab_cell_flash-0.4.0.dist-info/licenses/LICENSE
jupyterlab_cell_flash-0.4.0.dist-info/RECORD
